getconti/__init__.py
getconti/getconti.py
getconti/datasource/Continents_to_CountryNames.csv
findContinent-1.0.0.dist-info/LICENSE
findContinent-1.0.0.dist-info/METADATA
findContinent-1.0.0.dist-info/WHEEL
findContinent-1.0.0.dist-info/top_level.txt
findContinent-1.0.0.dist-info/RECORD
