Metadata-Version: 2.1
Name: findContinent
Version: 1.0.0
Summary: This module can help you to get the continent of different countries
Home-page: https://github.com/meShubhamJha/getconti
Author: Shubham Jha
Author-email: sjha0090@gmail.com
License: MIT
Platform: UNKNOWN
Classifier: Programming Language :: Python :: 3
Classifier: Operating System :: OS Independent
Requires-Python: >3.5.2
License-File: LICENSE
Requires-Dist: pandas
